machette_lc_py/__init__.py
machette_lc_py/fileOps.py
machette_lc_py_dotHTM-0.0.4.dist-info/LICENSE.md
machette_lc_py_dotHTM-0.0.4.dist-info/METADATA
machette_lc_py_dotHTM-0.0.4.dist-info/WHEEL
machette_lc_py_dotHTM-0.0.4.dist-info/top_level.txt
machette_lc_py_dotHTM-0.0.4.dist-info/RECORD
